huaweicloudsdkcce/__init__.py
huaweicloudsdkcce/v3/__init__.py
huaweicloudsdkcce/v3/cce_async_client.py
huaweicloudsdkcce/v3/cce_client.py
huaweicloudsdkcce/v3/cce_exception_handler.py
huaweicloudsdkcce/v3/model/__init__.py
huaweicloudsdkcce/v3/model/access_policy.py
huaweicloudsdkcce/v3/model/access_policy_resp.py
huaweicloudsdkcce/v3/model/access_scope.py
huaweicloudsdkcce/v3/model/add_node.py
huaweicloudsdkcce/v3/model/add_node_list.py
huaweicloudsdkcce/v3/model/add_node_request.py
huaweicloudsdkcce/v3/model/add_node_response.py
huaweicloudsdkcce/v3/model/add_nodes_to_node_pool.py
huaweicloudsdkcce/v3/model/add_nodes_to_node_pool_list.py
huaweicloudsdkcce/v3/model/add_nodes_to_node_pool_request.py
huaweicloudsdkcce/v3/model/add_nodes_to_node_pool_response.py
huaweicloudsdkcce/v3/model/addon_check_request.py
huaweicloudsdkcce/v3/model/addon_check_spec.py
huaweicloudsdkcce/v3/model/addon_check_status.py
huaweicloudsdkcce/v3/model/addon_check_task.py
huaweicloudsdkcce/v3/model/addon_info.py
huaweicloudsdkcce/v3/model/addon_instance.py
huaweicloudsdkcce/v3/model/addon_instance_rollback_request.py
huaweicloudsdkcce/v3/model/addon_instance_status.py
huaweicloudsdkcce/v3/model/addon_metadata.py
huaweicloudsdkcce/v3/model/addon_risks.py
huaweicloudsdkcce/v3/model/addon_template.py
huaweicloudsdkcce/v3/model/alarm_info.py
huaweicloudsdkcce/v3/model/api_version_detail.py
huaweicloudsdkcce/v3/model/api_version_link.py
huaweicloudsdkcce/v3/model/authenticating_proxy.py
huaweicloudsdkcce/v3/model/authentication.py
huaweicloudsdkcce/v3/model/auto_generate_security_group_hardening_config_spec.py
huaweicloudsdkcce/v3/model/autopilot_authentication.py
huaweicloudsdkcce/v3/model/autopilot_cluster.py
huaweicloudsdkcce/v3/model/autopilot_cluster_endpoints.py
huaweicloudsdkcce/v3/model/autopilot_cluster_extend_param.py
huaweicloudsdkcce/v3/model/autopilot_cluster_information.py
huaweicloudsdkcce/v3/model/autopilot_cluster_information_spec.py
huaweicloudsdkcce-3.1.184.dist-info/METADATA
huaweicloudsdkcce-3.1.184.dist-info/WHEEL
huaweicloudsdkcce-3.1.184.dist-info/licenses/LICENSE
huaweicloudsdkcce-3.1.184.dist-info/RECORD
